[
{"category":null,"reshared_count":0,"layout":2,"from_subscription":false,"title":"说：","text":"the golden thread","created_at":"2014-01-24 21:56:53","can_reply":1,"attachments":[{"description":"","title":"","media":[],"caption":"","href":"","type":"image","properties":{}}],"entities":{"user_mentions":[],"topics":[],"urls":[]},"like_count":0,"comments_count":0,"source":{},"is_follow":false,"has_photo":true,"type":0,"id":1320135502,"user":{"uid":"germinga","description":"","small_avatar":"http:\/\/img3.douban.com\/icon\/u3326311-19.jpg","large_avatar":"http:\/\/img3.douban.com\/icon\/ul3326311-19.jpg","type":"user","id":"3326311","screen_name":"Germinga"}},
{"category":null,"reshared_count":0,"layout":1,"from_subscription":false,"title":"关注","text":"","created_at":"2014-01-23 19:13:20","can_reply":0,"attachments":[{"description":"头像：木绣球\n\n本人长期无证从事各种疑难植物（多肉除外，兰花除外，蕨类除外，禾...","title":"adel","media":[{"src":"http:\/\/img3.douban.com\/view\/status\/small\/public\/2PwzpX.jpg","sizes":{"small":[128,84],"ismall":[null,null],"median":[160,106],"raw":[160,106]},"secret_pid":"","original_src":"http:\/\/img3.douban.com\/icon\/ul3052876-21.jpg","href":"http:\/\/dou.bz\/03O6dK","type":"image"}],"properties":{},"caption":"","href":"http:\/\/www.douban.com\/people\/des.fleurs\/","type":"","expaned_href":"http:\/\/www.douban.com\/people\/des.fleurs\/"}],"entities":{"user_mentions":[],"topics":[],"urls":[]},"like_count":0,"comments_count":0,"source":{},"is_follow":true,"has_photo":false,"type":0,"id":1319215014,"user":{"uid":"germinga","description":"","small_avatar":"http:\/\/img3.douban.com\/icon\/u3326311-19.jpg","large_avatar":"http:\/\/img3.douban.com\/icon\/ul3326311-19.jpg","type":"user","id":"3326311","screen_name":"Germinga"}},
{	"category":null,
	"reshared_count":0,
	"layout":3,
	"from_subscription":false,
	"title":"推荐照片",
	"text":"",
	"created_at":"2014-01-23 19:13:00",
	"can_reply":1,
	"attachments":[{
			"description":"飘香藤",
			"title":"相册－ [收集] 藤蔓 的照片",
			"media":[{
					"src":"http:\/\/img3.douban.com\/view\/status\/small\/public\/4vgFjx.jpg",
					"sizes":{
						"small":[128,85],
						"ismall":[null,null],
						"median":[460,306],
						"raw":[600,400]},
					"secret_pid":"",
					"original_src":"http:\/\/img3.douban.com\/view\/photo\/photo\/public\/p415938085.jpg",
					"href":"http:\/\/dou.bz\/0ct8Yw","type":"image"}],
				"properties":{},"caption":"","href":"http:\/\/dou.bz\/0ct8Yw","type":"","expaned_href":"http:\/\/www.douban.com\/photos\/photo\/415938085\/"}],
	"entities":{
		"user_mentions":[],
		"topics":[],
		"urls":[]},
	"like_count":0,
	"comments_count":0,
	"source":{},
	"is_follow":false,
	"has_photo":true,
	"type":0,
	"id":1319214880,
	"user":{
		"uid":"germinga",
		"description":"",
		"small_avatar":"http:\/\/img3.douban.com\/icon\/u3326311-19.jpg",
		"large_avatar":"http:\/\/img3.douban.com\/icon\/ul3326311-19.jpg",
		"type":"user",
		"id":"3326311",
		"screen_name":"Germinga"}},
{"category":null,"reshared_count":0,"layout":3,"from_subscription":false,"title":"推荐照片","text":"","created_at":"2014-01-23 19:12:19","can_reply":1,"attachments":[{"description":"蓝雪花","title":"相册－ [收集] 藤蔓 的照片","media":[{"src":"http:\/\/img3.douban.com\/view\/status\/small\/public\/2SYioi.jpg","sizes":{"small":[128,88],"ismall":[230,155],"median":[460,317],"raw":[580,400]},"secret_pid":"","original_src":"http:\/\/img5.douban.com\/view\/photo\/photo\/public\/p416603629.jpg","href":"http:\/\/dou.bz\/0NexjI","type":"image"}],"properties":{},"caption":"","href":"http:\/\/dou.bz\/0NexjI","type":"","expaned_href":"http:\/\/www.douban.com\/photos\/photo\/416603629\/"}],"entities":{"user_mentions":[],"topics":[],"urls":[]},"like_count":0,"comments_count":0,"source":{},"is_follow":false,"has_photo":true,"type":0,"id":1319214617,"user":{"uid":"germinga","description":"","small_avatar":"http:\/\/img3.douban.com\/icon\/u3326311-19.jpg","large_avatar":"http:\/\/img3.douban.com\/icon\/ul3326311-19.jpg","type":"user","id":"3326311","screen_name":"Germinga"}},
{"category":null,"reshared_count":0,"layout":1,"from_subscription":false,"title":"想读","text":"","created_at":"2014-01-21 20:04:53","can_reply":1,"attachments":[{"description":"[俄] 帕斯捷尔纳克 \/ 上海译文出版社","title":"阿佩莱斯线条","media":[{"src":"http:\/\/img5.douban.com\/view\/status\/small\/public\/3ICf19.jpg","sizes":{"small":[67,97],"ismall":[null,null],"median":[67,97],"raw":[67,97]},"secret_pid":"","original_src":"http:\/\/img3.douban.com\/spic\/s6955772.jpg","href":"http:\/\/dou.bz\/0gVWKS","type":"image"}],"properties":{},"caption":"","href":"http:\/\/dou.bz\/0gVWKS","type":"book","expaned_href":"http:\/\/book.douban.com\/subject\/6711376\/"}],"entities":{"user_mentions":[],"topics":[],"urls":[]},"like_count":0,"comments_count":0,"source":{},"is_follow":false,"has_photo":false,"type":0,"id":1317768873,"user":{"uid":"germinga","description":"","small_avatar":"http:\/\/img3.douban.com\/icon\/u3326311-19.jpg","large_avatar":"http:\/\/img3.douban.com\/icon\/ul3326311-19.jpg","type":"user","id":"3326311","screen_name":"Germinga"}},
{"category":null,"reshared_count":0,"layout":1,"from_subscription":false,"title":"读过[score]5[\/score]","text":"いやされた","created_at":"2014-01-19 19:20:29","can_reply":1,"attachments":[{"description":"〔苏〕鲍里斯·帕斯捷尔纳克 \/ 人民文学出版社","title":"日瓦戈医生","media":[{"src":"http:\/\/img3.douban.com\/view\/status\/small\/public\/4g4Wga.jpg","sizes":{"small":[68,96],"ismall":[230,155],"median":[68,96],"raw":[68,96]},"secret_pid":"","original_src":"http:\/\/img5.douban.com\/spic\/s1659397.jpg","href":"http:\/\/dou.bz\/3AkvbZ","type":"image"}],"properties":{},"caption":"","href":"http:\/\/dou.bz\/3AkvbZ","type":"book","expaned_href":"http:\/\/book.douban.com\/subject\/1469878\/"}],"entities":{"user_mentions":[],"topics":[],"urls":[]},"like_count":0,"comments_count":0,"source":{},"is_follow":false,"has_photo":false,"type":0,"id":1316323086,"user":{"uid":"germinga","description":"","small_avatar":"http:\/\/img3.douban.com\/icon\/u3326311-19.jpg","large_avatar":"http:\/\/img3.douban.com\/icon\/ul3326311-19.jpg","type":"user","id":"3326311","screen_name":"Germinga"}},
{"category":null,"reshared_count":0,"layout":2,"from_subscription":false,"title":"说：","text":"气死我了 这帮没人性的家伙","created_at":"2014-01-16 09:00:50","can_reply":1,"attachments":[{"description":"","title":"","media":[],"caption":"","href":"","type":"image","properties":{}}],"entities":{"user_mentions":[],"topics":[],"urls":[]},"like_count":0,"comments_count":11,"source":{},"is_follow":false,"has_photo":true,"type":0,"id":1314002091,"user":{"uid":"germinga","description":"","small_avatar":"http:\/\/img3.douban.com\/icon\/u3326311-19.jpg","large_avatar":"http:\/\/img3.douban.com\/icon\/ul3326311-19.jpg","type":"user","id":"3326311","screen_name":"Germinga"}},
{"category":null,"reshared_count":0,"layout":1,"from_subscription":false,"title":"推荐小组话题","text":"","created_at":"2014-01-03 23:03:09","can_reply":1,"attachments":[{"description":"新人啊新人 拜组来了\r\n希望我们这个组茁壮成长啊：）\r\n\r\n\r\n\r\n明智光秀  \r\n顺逆无二道，大道贯心源， 五十五年梦，醒时归一眠。  \r\n\r\n足利义辉  \r\n梅雨如露亦如泪，杜鹃载吾名至云。  \r\n\r\n尼...","title":"日本战国名将辞世诗句 转","media":[],"properties":{},"caption":"","href":"http:\/\/dou.bz\/1v0lMW","type":"com.douban.group","expaned_href":"http:\/\/www.douban.com\/group\/topic\/2681268\/"}],"entities":{"user_mentions":[],"topics":[],"urls":[]},"like_count":0,"comments_count":0,"source":{},"is_follow":false,"has_photo":false,"type":0,"id":1302906944,"user":{"uid":"germinga","description":"","small_avatar":"http:\/\/img3.douban.com\/icon\/u3326311-19.jpg","large_avatar":"http:\/\/img3.douban.com\/icon\/ul3326311-19.jpg","type":"user","id":"3326311","screen_name":"Germinga"}},
{"category":null,"reshared_count":0,"layout":2,"from_subscription":false,"title":"说：","text":"大事の義は、人に談合せず、一心に究めたるがよし。 \r\n伊達政宗","created_at":"2014-01-03 22:53:48","can_reply":1,"attachments":[{"description":"","title":"","media":[],"caption":"","href":"","type":"image","properties":{}}],"entities":{"user_mentions":[],"topics":[],"urls":[]},"like_count":0,"comments_count":0,"source":{},"is_follow":false,"has_photo":true,"type":0,"id":1302900397,"user":{"uid":"germinga","description":"","small_avatar":"http:\/\/img3.douban.com\/icon\/u3326311-19.jpg","large_avatar":"http:\/\/img3.douban.com\/icon\/ul3326311-19.jpg","type":"user","id":"3326311","screen_name":"Germinga"}},
{"category":null,"reshared_count":1,"layout":1,"from_subscription":false,"title":"推荐日记","text":"","created_at":"2013-12-31 09:03:53","can_reply":1,"attachments":[{"description":"非常高兴能在豆瓣认识那么多学习书法的友邻，从大家身上我也学到了很多东西。写这篇文章的目的是想把我自己学书过程中遇到的一些问题和大家分享，其中大部分都是初学过程中比较容易忽视的问...","title":"你真的会写“必”字吗？","media":[],"properties":{},"caption":"","href":"http:\/\/dou.bz\/3tNXMv","type":"com.douban.people","expaned_href":"http:\/\/www.douban.com\/note\/270294854\/"}],"entities":{"user_mentions":[],"topics":[],"urls":[]},"like_count":0,"comments_count":0,"source":{},"is_follow":false,"has_photo":false,"type":0,"id":1298600477,"user":{"uid":"germinga","description":"","small_avatar":"http:\/\/img3.douban.com\/icon\/u3326311-19.jpg","large_avatar":"http:\/\/img3.douban.com\/icon\/ul3326311-19.jpg","type":"user","id":"3326311","screen_name":"Germinga"}},
{"category":null,"reshared_count":0,"layout":2,"from_subscription":false,"title":"说：","text":"Oh I don't like the cgs units...","created_at":"2013-12-30 23:20:30","can_reply":1,"attachments":[{"description":"","title":"","media":[],"caption":"","href":"","type":"image","properties":{}}],"entities":{"user_mentions":[],"topics":[],"urls":[]},"like_count":0,"comments_count":1,"source":{},"is_follow":false,"has_photo":true,"type":0,"id":1298503110,"user":{"uid":"germinga","description":"","small_avatar":"http:\/\/img3.douban.com\/icon\/u3326311-19.jpg","large_avatar":"http:\/\/img3.douban.com\/icon\/ul3326311-19.jpg","type":"user","id":"3326311","screen_name":"Germinga"}},
{"category":null,"reshared_count":0,"layout":2,"from_subscription":false,"title":"说：","text":"今天看到一个词儿 house theoretician","created_at":"2013-12-27 10:54:33","can_reply":1,"attachments":[{"description":"","title":"","media":[],"caption":"","href":"","type":"image","properties":{}}],"entities":{"user_mentions":[],"topics":[],"urls":[]},"like_count":0,"comments_count":0,"source":{},"is_follow":false,"has_photo":true,"type":0,"id":1294484086,"user":{"uid":"germinga","description":"","small_avatar":"http:\/\/img3.douban.com\/icon\/u3326311-19.jpg","large_avatar":"http:\/\/img3.douban.com\/icon\/ul3326311-19.jpg","type":"user","id":"3326311","screen_name":"Germinga"}},
{"category":null,"reshared_count":1,"layout":3,"from_subscription":false,"title":"推荐照片","text":"","created_at":"2013-12-21 23:29:07","can_reply":1,"attachments":[{"description":"取之无禁，用之不竭，是造物者之无尽藏也，而吾与子之所共适。”\r\n　　客喜而笑，洗盏更酌。肴核既尽，杯盘狼籍。相与枕藉乎舟中，不知东方之既白。","title":"相册－文徵明 赤壁赋 的照片","media":[{"src":"http:\/\/img3.douban.com\/view\/status\/small\/public\/197FAN.jpg","sizes":{"small":[80,128],"ismall":[230,155],"median":[375,600],"raw":[375,600]},"secret_pid":"","original_src":"http:\/\/img5.douban.com\/view\/photo\/photo\/public\/p1356790189.jpg","href":"http:\/\/dou.bz\/0zhFim","type":"image"}],"properties":{},"caption":"","href":"http:\/\/dou.bz\/0zhFim","type":"","expaned_href":"http:\/\/www.douban.com\/photos\/photo\/1356790189\/"}],"entities":{"user_mentions":[],"topics":[],"urls":[]},"like_count":0,"comments_count":0,"source":{},"is_follow":false,"has_photo":true,"type":0,"id":1290063813,"user":{"uid":"germinga","description":"","small_avatar":"http:\/\/img3.douban.com\/icon\/u3326311-19.jpg","large_avatar":"http:\/\/img3.douban.com\/icon\/ul3326311-19.jpg","type":"user","id":"3326311","screen_name":"Germinga"}},
{"category":null,"reshared_count":1,"layout":3,"from_subscription":false,"title":"推荐照片","text":"","created_at":"2013-12-21 23:27:43","can_reply":1,"attachments":[{"description":"","title":"相册－前后赤壁赋 的照片","media":[{"src":"http:\/\/img3.douban.com\/view\/status\/small\/public\/1kUd5u.jpg","sizes":{"small":[90,128],"ismall":[230,155],"median":[424,600],"raw":[424,600]},"secret_pid":"","original_src":"http:\/\/img3.douban.com\/view\/photo\/photo\/public\/p779326982.jpg","href":"http:\/\/dou.bz\/0epHPa","type":"image"}],"properties":{},"caption":"","href":"http:\/\/dou.bz\/0epHPa","type":"","expaned_href":"http:\/\/www.douban.com\/photos\/photo\/779326982\/"}],"entities":{"user_mentions":[],"topics":[],"urls":[]},"like_count":0,"comments_count":0,"source":{},"is_follow":false,"has_photo":true,"type":0,"id":1290062943,"user":{"uid":"germinga","description":"","small_avatar":"http:\/\/img3.douban.com\/icon\/u3326311-19.jpg","large_avatar":"http:\/\/img3.douban.com\/icon\/ul3326311-19.jpg","type":"user","id":"3326311","screen_name":"Germinga"}},
{"category":null,"reshared_count":0,"layout":1,"from_subscription":false,"title":"在读[score]0[\/score]","text":"","created_at":"2013-12-21 17:25:47","can_reply":1,"attachments":[{"description":"Of Matter and Forces in the Physical World \/ Abraham Pais \/ Oxford University Press, USA","title":"Inward Bound","media":[{"src":"http:\/\/img3.douban.com\/view\/status\/small\/public\/08VlnP.jpg","sizes":{"small":[64,101],"ismall":[230,155],"median":[64,101],"raw":[64,101]},"secret_pid":"","original_src":"http:\/\/img5.douban.com\/spic\/s4201318.jpg","href":"http:\/\/dou.bz\/0VzBne","type":"image"}],"properties":{},"caption":"","href":"http:\/\/dou.bz\/0VzBne","type":"book","expaned_href":"http:\/\/book.douban.com\/subject\/2880701\/"}],"entities":{"user_mentions":[],"topics":[],"urls":[]},"like_count":0,"comments_count":0,"source":{},"is_follow":false,"has_photo":false,"type":0,"id":1289676107,"user":{"uid":"germinga","description":"","small_avatar":"http:\/\/img3.douban.com\/icon\/u3326311-19.jpg","large_avatar":"http:\/\/img3.douban.com\/icon\/ul3326311-19.jpg","type":"user","id":"3326311","screen_name":"Germinga"}},
{"category":null,"reshared_count":0,"layout":2,"from_subscription":false,"title":"说：","text":"终于又装上mathematica可以玩了","created_at":"2013-12-19 16:43:46","can_reply":1,"attachments":[{"description":"","title":"","media":[],"caption":"","href":"","type":"image","properties":{}}],"entities":{"user_mentions":[],"topics":[],"urls":[]},"like_count":0,"comments_count":0,"source":{},"is_follow":false,"has_photo":true,"type":0,"id":1287835045,"user":{"uid":"germinga","description":"","small_avatar":"http:\/\/img3.douban.com\/icon\/u3326311-19.jpg","large_avatar":"http:\/\/img3.douban.com\/icon\/ul3326311-19.jpg","type":"user","id":"3326311","screen_name":"Germinga"}},
{"category":null,"reshared_count":0,"layout":3,"from_subscription":false,"title":"推荐照片","text":"","created_at":"2013-12-16 16:42:58","can_reply":1,"attachments":[{"description":"","title":"相册－冻死在那里也值得。。。 的照片","media":[{"src":"http:\/\/img3.douban.com\/view\/status\/small\/public\/1uolyF.jpg","sizes":{"small":[128,128],"ismall":[230,155],"median":[460,460],"raw":[600,600]},"secret_pid":"","original_src":"http:\/\/img5.douban.com\/view\/photo\/photo\/public\/p2162869118.jpg","href":"http:\/\/dou.bz\/0UlYjW","type":"image"}],"properties":{},"caption":"","href":"http:\/\/dou.bz\/0UlYjW","type":"","expaned_href":"http:\/\/www.douban.com\/photos\/photo\/2162869118\/"}],"entities":{"user_mentions":[],"topics":[],"urls":[]},"like_count":0,"comments_count":0,"source":{},"is_follow":false,"has_photo":true,"type":0,"id":1284927753,"user":{"uid":"germinga","description":"","small_avatar":"http:\/\/img3.douban.com\/icon\/u3326311-19.jpg","large_avatar":"http:\/\/img3.douban.com\/icon\/ul3326311-19.jpg","type":"user","id":"3326311","screen_name":"Germinga"}},
{"category":null,"reshared_count":0,"layout":1,"from_subscription":false,"title":"推荐小组话题","text":"","created_at":"2013-12-16 16:19:11","can_reply":1,"attachments":[{"description":"优秀国外Podcast汇总\r\n播客百科，自由的百科全书\r\n一、视频Podcast：\r\n\r\n1、大媒体\r\n\r\n路透社视频新闻 \r\n英国太阳报：http:\/\/www.thesun.co.uk\/ （英国报纸中第一家提供视频，还没有RSS) \r\n...","title":"优秀国外Podcast汇总","media":[],"properties":{},"caption":"","href":"http:\/\/dou.bz\/2bIpwc","type":"com.douban.group","expaned_href":"http:\/\/www.douban.com\/group\/topic\/1790663\/"}],"entities":{"user_mentions":[],"topics":[],"urls":[]},"like_count":0,"comments_count":0,"source":{},"is_follow":false,"has_photo":false,"type":0,"id":1284912051,"user":{"uid":"germinga","description":"","small_avatar":"http:\/\/img3.douban.com\/icon\/u3326311-19.jpg","large_avatar":"http:\/\/img3.douban.com\/icon\/ul3326311-19.jpg","type":"user","id":"3326311","screen_name":"Germinga"}},
{"category":null,"reshared_count":0,"layout":1,"from_subscription":false,"title":"想读","text":"","created_at":"2013-12-16 12:02:56","can_reply":1,"attachments":[{"description":"Shoenberg, D.","title":"Magnetic Oscillations in Metals","media":[{"src":"http:\/\/img5.douban.com\/view\/status\/small\/public\/3a4NC9.jpg","sizes":{"small":[66,99],"ismall":[230,155],"median":[66,99],"raw":[66,99]},"secret_pid":"","original_src":"http:\/\/img3.douban.com\/spic\/s13858801.jpg","href":"http:\/\/dou.bz\/2U4f9y","type":"image"}],"properties":{},"caption":"","href":"http:\/\/dou.bz\/2U4f9y","type":"book","expaned_href":"http:\/\/book.douban.com\/subject\/6096168\/"}],"entities":{"user_mentions":[],"topics":[],"urls":[]},"like_count":0,"comments_count":0,"source":{},"is_follow":false,"has_photo":false,"type":0,"id":1284577522,"user":{"uid":"germinga","description":"","small_avatar":"http:\/\/img3.douban.com\/icon\/u3326311-19.jpg","large_avatar":"http:\/\/img3.douban.com\/icon\/ul3326311-19.jpg","type":"user","id":"3326311","screen_name":"Germinga"}},
{"category":null,"reshared_count":0,"layout":null,"from_subscription":false,"title":"说：","text":"","created_at":"2013-12-10 22:11:13","can_reply":1,"attachments":[],"entities":{"user_mentions":[],"topics":[],"urls":[]},"like_count":0,"comments_count":0,"source":{},"is_follow":false,"has_photo":false,"reshared_status":{"category":null,"reshared_count":145,"layout":2,"from_subscription":false,"title":"说：","text":"一会我家傻黑子睡醒了我去试试~！！报复性的挠挠","created_at":"2013-12-08 14:55:45","can_reply":1,"attachments":[{"description":"","title":"","media":[{"src":"http:\/\/img3.douban.com\/view\/status\/small\/public\/66bc2a27fb6db3b.jpg","sizes":{"small":[61,128],"ismall":[230,155],"median":[460,956],"raw":[486,1011]},"secret_pid":"","original_src":"","href":"http:\/\/dou.bz\/1utW9M","type":"image"}],"caption":"","href":"","type":"image","properties":{}}],"entities":{"user_mentions":[],"topics":[],"urls":[]},"like_count":51,"comments_count":8,"source":{},"is_follow":false,"has_photo":true,"type":0,"id":1277107723,"user":{"uid":"yesenia1988","description":"","small_avatar":"http:\/\/img3.douban.com\/icon\/u39467514-56.jpg","large_avatar":"http:\/\/img3.douban.com\/icon\/ul39467514-56.jpg","type":"user","id":"39467514","screen_name":"张卯"}},"type":0,"id":1279644147,"user":{"uid":"germinga","description":"","small_avatar":"http:\/\/img3.douban.com\/icon\/u3326311-19.jpg","large_avatar":"http:\/\/img3.douban.com\/icon\/ul3326311-19.jpg","type":"user","id":"3326311","screen_name":"Germinga"}}
]